{
  "schema_version": 1,
  "tasks": [
    {
      "activation_status": "paid",
      "difficulty_band": "easy",
      "domain_id": "lean",
      "frontier_depth": 14,
      "id": "lemma.procedural.b0cdba4b693ebc3a",
      "imports": [
        "Mathlib.Algebra.Ring.AddAut",
        "Mathlib.Algebra.Ring.SumsOfSquares",
        "Mathlib.Algebra.Ring.Basic"
      ],
      "lean_toolchain": "leanprover/lean4:v4.30.0-rc2",
      "mathlib_rev": "5450b53e5ddc75d46418fabb605edbf36bd0beb6",
      "metadata": {
        "activation_status": "paid",
        "anchor_block": 7201800,
        "baseline_solved": false,
        "baseline_solver": null,
        "canonical_hash": "99d5425cf7f1824b6f89aa3525a19a041fe2a735a1dae5ad89d0e9730fbfd920",
        "citation_alpha_basis_points": 5000,
        "citation_weight_cap_micros": 64000000,
        "citation_window_tempos": 2000,
        "drand_round": 28980552,
        "gate_receipt_sha256": "2ea9df00e7bb2bddaab8fbad0575cadd76e17bf71696d27ed4e87feacf08fecd",
        "gate_runner": "lean",
        "gate_version": "lemma-procedural-gates-v3",
        "generation_seed": "fe40d272cad1d59ab1869a8489d908fc5c32848a13501244397700f4ccd24831",
        "kernel_canonical_hash": "99d5425cf7f1824b6f89aa3525a19a041fe2a735a1dae5ad89d0e9730fbfd920",
        "kernel_canonical_name": "LemmaProceduralGate.kernel_normal_form",
        "license_state": "clean_open",
        "mutation_chain": [
          {
            "input_hash": "b624ebca9ab4263ab7540da39fe24a37460e1d9f037fa9122e4097a107868020",
            "operator": "strengthen",
            "output_hash": "7c571a7058cbc4c5620106f7d6fdf3d51b94a41d880098ef4c65a172e74ce464",
            "params": {
              "engine": "lean_ast_elaborator",
              "peer_source_id": "lemma.mathlib_snapshot.IsSumSq.sum_isSquare",
              "peer_target_sha256": "9360e7b70d06bc2ea8d7965f57248b302fc93b5561bdae1a1a9033dcc715e373",
              "peer_theorem_name": "IsSumSq.sum_isSquare",
              "rule": "conjoin_peer_conclusion"
            }
          },
          {
            "input_hash": "7c571a7058cbc4c5620106f7d6fdf3d51b94a41d880098ef4c65a172e74ce464",
            "operator": "strengthen",
            "output_hash": "560af871eed29459f2ebb4546c01be0680b681fa67b34caa32b075b6b90e731d",
            "params": {
              "engine": "lean_ast_elaborator",
              "peer_source_id": "lemma.mathlib_snapshot.noZeroDivisors_tfae",
              "peer_target_sha256": "46fda61b5bf684067dbb79be6cc3ccf82f05b6915d0599f1fde4d3c80a1264dc",
              "peer_theorem_name": "noZeroDivisors_tfae",
              "rule": "conjoin_peer_conclusion"
            }
          }
        ],
        "mutation_depth": 2,
        "novelty_cache_entries": 1,
        "novelty_cache_sha256": "1e32c7405aa77f76d3d5a318d9d8882ceff2219062dbdf0d4471f64b49267ccd",
        "novelty_cache_version": "lemma-novelty-cache-v1",
        "novelty_status": "passed",
        "operator_bundle_hash": "f8d88c884199c0ffe47fc0089803a5d38c1bf8b38395162a298a5c65e04592e1",
        "operator_bundle_version": "lemma-procedural-depth2-v3",
        "prop_gate_passed": true,
        "prop_gate_reason": "ok",
        "slot_weight": 1.485,
        "slot_weight_basis_points": 1485,
        "slot_weight_inputs": {
          "citation_weight": 1.0,
          "dependency_depth": 0,
          "direct_dependency_count": 0,
          "import_breadth": 3,
          "import_depth": 0,
          "import_graph_entries": 16,
          "import_graph_resolved": true,
          "import_graph_sha256": "8acf594d0f836405445898da44f610f628851b071c10767b3518c35e4025dcb7",
          "import_graph_version": "lemma-import-graph-v1",
          "kernel_dependencies_recorded": false,
          "lemma_rows_used_count": 0,
          "missing_import_count": 0,
          "mutation_depth": 2,
          "transitive_dependency_count": 0,
          "transitive_dependency_hash": "c24afc8b44f3af9a2be35710a0db9da3a8e3e90acbc8ae7a981d2c74968f9cae"
        },
        "slot_weight_version": "lemma-slot-weight-v3",
        "source_pool_hash": "180508097fb11c3c12f416833b077bfdd40da9fbbdb54c3e72572a4969d6efe0",
        "source_pool_receipt_sha256": "bc9f8af90992a8a5ef66e42d66c2c0acecd322124b53d2042636c4195edb2d63",
        "source_pool_receipt_version": "lemma-source-pool-receipt-v1",
        "source_pool_source_count": 39,
        "source_pool_stream_counts": {
          "mathlib_snapshot": 39
        },
        "source_sampling_version": "lemma-source-sampling-v1",
        "source_target_sha256": "4ff8a3c35f7b5ac4b29af9213c5a40a90c39ac9793c3cc5670ba33619d66398f",
        "source_task_id": "lemma.mathlib_snapshot.AddAut.mulRight_apply",
        "source_theorem_name": "AddAut.mulRight_apply",
        "statement_hash": "c693e6746f97431aa7486be1b5761ff6b11339da8772d0c2a3b40d1497f75354",
        "supply_mode": "procedural",
        "tempo": 20005,
        "triviality_budget_heartbeats": 200000,
        "triviality_budget_s": 200000,
        "triviality_budget_version": "lemma-triviality-retarget-v1",
        "triviality_burn_rate_basis_points": null,
        "triviality_checked": true,
        "triviality_reason": "baseline_failed",
        "triviality_retarget_inputs": {
          "genesis_budget_heartbeats": 200000,
          "genesis_budget_s": 200000,
          "high_burn_basis_points": 7000,
          "latest_settlement_tempo": null,
          "low_burn_basis_points": 4000,
          "max_budget_heartbeats": 2000000,
          "max_budget_s": 2000000,
          "max_step_basis_points": 2500,
          "min_budget_heartbeats": 20000,
          "min_budget_s": 20000,
          "settlement_count": 0,
          "settlement_history_sha256": "4f53cda18c2baa0c0354bb5f9a3ecbe5ed12ab4d8e11ba873c2f11161202b945",
          "target_burn_basis_points": 5500,
          "target_tempo": 20005,
          "version": "lemma-triviality-retarget-v1",
          "window_tempos": 8
        },
        "triviality_stack": [
          "decide",
          "simp_all",
          "omega",
          "norm_num",
          "ring",
          "linarith",
          "nlinarith",
          "aesop"
        ],
        "typecheck_reason": "ok",
        "typechecked": true
      },
      "policy": "restricted_helpers",
      "queue_depth": 0,
      "queue_position": 0,
      "schema_version": 1,
      "source_license": "Apache-2.0",
      "source_ref": {
        "commit": "5450b53e5ddc75d46418fabb605edbf36bd0beb6",
        "kind": "procedural",
        "name": "tempo-20005-seq-15",
        "path": "Mathlib/Algebra/Ring/AddAut.lean"
      },
      "source_stream": "procedural",
      "statement": "theorem procedural_AddAut_mulRight_apply_b0cdba4b693e : ((\u2200 {R : Type _} [Semiring R] (u : R\u02e3) (x : R), (AddAut.mulRight u) x = x * \u2191u) \u2227\n    (\u2200 {R : Type _} [AddCommMonoid R] [Mul R] {\u03b9 : Type _} (I : Finset \u03b9) {x : \u03b9 \u2192 R} (hx : \u2200 i \u2208 I, IsSquare (x i)),\n      IsSumSq (\u2211 i \u2208 I, x i))) \u2227\n  (\u2200 {R : Type _} [NonUnitalNonAssocRing R],\n    [NoZeroDivisors R, IsLeftCancelMulZero R, IsRightCancelMulZero R, IsCancelMulZero R].TFAE) := by\n  sorry",
      "submission_stub": "import Mathlib.Algebra.Ring.AddAut\nimport Mathlib.Algebra.Ring.SumsOfSquares\nimport Mathlib.Algebra.Ring.Basic\n\nnamespace Submission\n\ntheorem procedural_AddAut_mulRight_apply_b0cdba4b693e : ((\u2200 {R : Type _} [Semiring R] (u : R\u02e3) (x : R), (AddAut.mulRight u) x = x * \u2191u) \u2227\n    (\u2200 {R : Type _} [AddCommMonoid R] [Mul R] {\u03b9 : Type _} (I : Finset \u03b9) {x : \u03b9 \u2192 R} (hx : \u2200 i \u2208 I, IsSquare (x i)),\n      IsSumSq (\u2211 i \u2208 I, x i))) \u2227\n  (\u2200 {R : Type _} [NonUnitalNonAssocRing R],\n    [NoZeroDivisors R, IsLeftCancelMulZero R, IsRightCancelMulZero R, IsCancelMulZero R].TFAE) := by\n  sorry\n\nend Submission\n",
      "target_sha256": "a4ff60deafd581bfebd667a38a4688ce4b04310de52a5cf434f5d360cbb40179",
      "task_version": 1,
      "theorem_name": "procedural_AddAut_mulRight_apply_b0cdba4b693e",
      "title": "Procedural AddAut.mulRight_apply",
      "triviality_status": "paid_easy",
      "type_expr": "((\u2200 {R : Type _} [Semiring R] (u : R\u02e3) (x : R), (AddAut.mulRight u) x = x * \u2191u) \u2227\n    (\u2200 {R : Type _} [AddCommMonoid R] [Mul R] {\u03b9 : Type _} (I : Finset \u03b9) {x : \u03b9 \u2192 R} (hx : \u2200 i \u2208 I, IsSquare (x i)),\n      IsSumSq (\u2211 i \u2208 I, x i))) \u2227\n  (\u2200 {R : Type _} [NonUnitalNonAssocRing R],\n    [NoZeroDivisors R, IsLeftCancelMulZero R, IsRightCancelMulZero R, IsCancelMulZero R].TFAE)",
      "verifier_id": "lake-build",
      "verifier_version": "lemma-lean-v1"
    },
    {
      "activation_status": "paid",
      "difficulty_band": "easy",
      "domain_id": "lean",
      "frontier_depth": 14,
      "id": "lemma.procedural.1d9c77e7b48c023d",
      "imports": [
        "Mathlib.Algebra.Ring.Basic",
        "Mathlib.Algebra.Ring.Associated",
        "Mathlib.Algebra.Ring.Associator"
      ],
      "lean_toolchain": "leanprover/lean4:v4.30.0-rc2",
      "mathlib_rev": "5450b53e5ddc75d46418fabb605edbf36bd0beb6",
      "metadata": {
        "activation_status": "paid",
        "anchor_block": 7201800,
        "baseline_solved": false,
        "baseline_solver": null,
        "canonical_hash": "30b3d520e469663dd3f4f9b97e43443cad8a36a238983aebcdb5881cf1eca224",
        "citation_alpha_basis_points": 5000,
        "citation_weight_cap_micros": 64000000,
        "citation_window_tempos": 2000,
        "drand_round": 28980552,
        "gate_receipt_sha256": "e967c10ff4fe43a66f26c5c0a36e59ea346be0f09c33c5ee1a95709abb1beec8",
        "gate_runner": "lean",
        "gate_version": "lemma-procedural-gates-v3",
        "generation_seed": "fe40d272cad1d59ab1869a8489d908fc5c32848a13501244397700f4ccd24831",
        "kernel_canonical_hash": "30b3d520e469663dd3f4f9b97e43443cad8a36a238983aebcdb5881cf1eca224",
        "kernel_canonical_name": "LemmaProceduralGate.kernel_normal_form",
        "license_state": "clean_open",
        "mutation_chain": [
          {
            "input_hash": "280e8d837e5cde6177ceec2ebbc41b22995fda0b2f1d45c5a4d868cecfac2dd2",
            "operator": "conjoin",
            "output_hash": "cd5e92fa6a97f8599cfc20b78cd7c59da008f5b364d9b773bb9f910c36eb027c",
            "params": {
              "engine": "lean_ast_elaborator",
              "mode": "peer_premise",
              "peer_source_id": "lemma.mathlib_snapshot.Associated.neg_left",
              "peer_target_sha256": "6ae2c203986024217ae7aa46b3f7900d609dd8136d10990e963a21918d39b7c8",
              "peer_theorem_name": "Associated.neg_left"
            }
          },
          {
            "input_hash": "cd5e92fa6a97f8599cfc20b78cd7c59da008f5b364d9b773bb9f910c36eb027c",
            "operator": "weaken",
            "output_hash": "337e1eb9d268d52e0740aad091234a3ba28eb7e4e04fbd115570b2cc17c0e301",
            "params": {
              "engine": "lean_ast_elaborator",
              "premise_syntax_hash": "15725789176860631979",
              "rule": "replace_first_premise_with_true"
            }
          }
        ],
        "mutation_depth": 2,
        "novelty_cache_entries": 1,
        "novelty_cache_sha256": "1e32c7405aa77f76d3d5a318d9d8882ceff2219062dbdf0d4471f64b49267ccd",
        "novelty_cache_version": "lemma-novelty-cache-v1",
        "novelty_status": "passed",
        "operator_bundle_hash": "f8d88c884199c0ffe47fc0089803a5d38c1bf8b38395162a298a5c65e04592e1",
        "operator_bundle_version": "lemma-procedural-depth2-v3",
        "prop_gate_passed": true,
        "prop_gate_reason": "ok",
        "slot_weight": 1.635,
        "slot_weight_basis_points": 1635,
        "slot_weight_inputs": {
          "citation_weight": 1.0,
          "dependency_depth": 1,
          "direct_dependency_count": 0,
          "import_breadth": 3,
          "import_depth": 0,
          "import_graph_entries": 16,
          "import_graph_resolved": true,
          "import_graph_sha256": "8acf594d0f836405445898da44f610f628851b071c10767b3518c35e4025dcb7",
          "import_graph_version": "lemma-import-graph-v1",
          "kernel_dependencies_recorded": false,
          "lemma_rows_used_count": 0,
          "missing_import_count": 0,
          "mutation_depth": 2,
          "transitive_dependency_count": 0,
          "transitive_dependency_hash": "ac4c9917ebb11e6bb4eb7176fdb7a84ab2cb2fc7a6edae54444806f3d38849f3"
        },
        "slot_weight_version": "lemma-slot-weight-v3",
        "source_pool_hash": "180508097fb11c3c12f416833b077bfdd40da9fbbdb54c3e72572a4969d6efe0",
        "source_pool_receipt_sha256": "bc9f8af90992a8a5ef66e42d66c2c0acecd322124b53d2042636c4195edb2d63",
        "source_pool_receipt_version": "lemma-source-pool-receipt-v1",
        "source_pool_source_count": 39,
        "source_pool_stream_counts": {
          "mathlib_snapshot": 39
        },
        "source_sampling_version": "lemma-source-sampling-v1",
        "source_target_sha256": "bff54a7def5ca7ac8381daf379cb82fcf591a61ca9a99b8caf786b07c0f4eac9",
        "source_task_id": "lemma.mathlib_snapshot.AddMonoidHom.map_mul_iff",
        "source_theorem_name": "AddMonoidHom.map_mul_iff",
        "statement_hash": "bdce761a72787c3b0f5812f52f980c04186029b403af716b55653740199a2998",
        "supply_mode": "procedural",
        "tempo": 20005,
        "triviality_budget_heartbeats": 200000,
        "triviality_budget_s": 200000,
        "triviality_budget_version": "lemma-triviality-retarget-v1",
        "triviality_burn_rate_basis_points": null,
        "triviality_checked": true,
        "triviality_reason": "baseline_failed",
        "triviality_retarget_inputs": {
          "genesis_budget_heartbeats": 200000,
          "genesis_budget_s": 200000,
          "high_burn_basis_points": 7000,
          "latest_settlement_tempo": null,
          "low_burn_basis_points": 4000,
          "max_budget_heartbeats": 2000000,
          "max_budget_s": 2000000,
          "max_step_basis_points": 2500,
          "min_budget_heartbeats": 20000,
          "min_budget_s": 20000,
          "settlement_count": 0,
          "settlement_history_sha256": "4f53cda18c2baa0c0354bb5f9a3ecbe5ed12ab4d8e11ba873c2f11161202b945",
          "target_burn_basis_points": 5500,
          "target_tempo": 20005,
          "version": "lemma-triviality-retarget-v1",
          "window_tempos": 8
        },
        "triviality_stack": [
          "decide",
          "simp_all",
          "omega",
          "norm_num",
          "ring",
          "linarith",
          "nlinarith",
          "aesop"
        ],
        "typecheck_reason": "ok",
        "typechecked": true
      },
      "policy": "restricted_helpers",
      "queue_depth": 1,
      "queue_position": 1,
      "schema_version": 1,
      "source_license": "Apache-2.0",
      "source_ref": {
        "commit": "5450b53e5ddc75d46418fabb605edbf36bd0beb6",
        "kind": "procedural",
        "name": "tempo-20005-seq-12",
        "path": "Mathlib/Algebra/Ring/Basic.lean"
      },
      "source_stream": "procedural",
      "statement": "theorem procedural_AddMonoidHom_map_mul_iff_1d9c77e7b48c : True \u2192\n  ((\u2200 {R : Type _} {S : Type _} [NonUnitalNonAssocSemiring R] [NonUnitalNonAssocSemiring S] (f : R \u2192+ S),\n    (\u2200 (x y : R), f (x * y) = f x * f y) \u2194 AddMonoidHom.mul.compr\u2082 f = (AddMonoidHom.mul.comp f).compl\u2082 f)) := by\n  sorry",
      "submission_stub": "import Mathlib.Algebra.Ring.Basic\nimport Mathlib.Algebra.Ring.Associated\nimport Mathlib.Algebra.Ring.Associator\n\nnamespace Submission\n\ntheorem procedural_AddMonoidHom_map_mul_iff_1d9c77e7b48c : True \u2192\n  ((\u2200 {R : Type _} {S : Type _} [NonUnitalNonAssocSemiring R] [NonUnitalNonAssocSemiring S] (f : R \u2192+ S),\n    (\u2200 (x y : R), f (x * y) = f x * f y) \u2194 AddMonoidHom.mul.compr\u2082 f = (AddMonoidHom.mul.comp f).compl\u2082 f)) := by\n  sorry\n\nend Submission\n",
      "target_sha256": "add2adb32e0da3f226b1788145871dba00419ee97620ba6c800774a2c87494c6",
      "task_version": 1,
      "theorem_name": "procedural_AddMonoidHom_map_mul_iff_1d9c77e7b48c",
      "title": "Procedural AddMonoidHom.map_mul_iff",
      "triviality_status": "paid_easy",
      "type_expr": "True \u2192\n  ((\u2200 {R : Type _} {S : Type _} [NonUnitalNonAssocSemiring R] [NonUnitalNonAssocSemiring S] (f : R \u2192+ S),\n    (\u2200 (x y : R), f (x * y) = f x * f y) \u2194 AddMonoidHom.mul.compr\u2082 f = (AddMonoidHom.mul.comp f).compl\u2082 f))",
      "verifier_id": "lake-build",
      "verifier_version": "lemma-lean-v1"
    },
    {
      "activation_status": "paid",
      "difficulty_band": "easy",
      "domain_id": "lean",
      "frontier_depth": 14,
      "id": "lemma.procedural.1fafeb8df2638315",
      "imports": [
        "Mathlib.Algebra.Ring.Basic"
      ],
      "lean_toolchain": "leanprover/lean4:v4.30.0-rc2",
      "mathlib_rev": "5450b53e5ddc75d46418fabb605edbf36bd0beb6",
      "metadata": {
        "activation_status": "paid",
        "anchor_block": 7201800,
        "baseline_solved": false,
        "baseline_solver": null,
        "canonical_hash": "c0b74e892ce783d9c977dc2c43c6bc1aa826b4186f7e96d85d786f111c72f5a8",
        "citation_alpha_basis_points": 5000,
        "citation_weight_cap_micros": 64000000,
        "citation_window_tempos": 2000,
        "drand_round": 28980552,
        "gate_receipt_sha256": "d3c45c39f93e6cc1e9e60b3a3c7a78b6b69f5203842f071930a524d346bd0cad",
        "gate_runner": "lean",
        "gate_version": "lemma-procedural-gates-v3",
        "generation_seed": "fe40d272cad1d59ab1869a8489d908fc5c32848a13501244397700f4ccd24831",
        "kernel_canonical_hash": "c0b74e892ce783d9c977dc2c43c6bc1aa826b4186f7e96d85d786f111c72f5a8",
        "kernel_canonical_name": "LemmaProceduralGate.kernel_normal_form",
        "license_state": "clean_open",
        "mutation_chain": [
          {
            "input_hash": "9c6be189b109126b7b2503fd2b7cfdb891c44f75137d5cf088d1517734627606",
            "operator": "generalize",
            "output_hash": "1a3b2ebdd1935942885dae619a7d572d760fa40ee849b32682b1a83abd9f030a",
            "params": {
              "binder": "lemma_p0_a6a8d5",
              "binder_type": "Prop",
              "engine": "lean_ast_elaborator",
              "target": "fresh_prop_hypothesis"
            }
          },
          {
            "input_hash": "1a3b2ebdd1935942885dae619a7d572d760fa40ee849b32682b1a83abd9f030a",
            "operator": "weaken",
            "output_hash": "0a0c40f8ef3f04ecabe6ef1109451a65d00031e31767a59ffa13b5a6127a16ea",
            "params": {
              "engine": "lean_ast_elaborator",
              "rule": "false_disjunct"
            }
          }
        ],
        "mutation_depth": 2,
        "novelty_cache_entries": 1,
        "novelty_cache_sha256": "1e32c7405aa77f76d3d5a318d9d8882ceff2219062dbdf0d4471f64b49267ccd",
        "novelty_cache_version": "lemma-novelty-cache-v1",
        "novelty_status": "passed",
        "operator_bundle_hash": "f8d88c884199c0ffe47fc0089803a5d38c1bf8b38395162a298a5c65e04592e1",
        "operator_bundle_version": "lemma-procedural-depth2-v3",
        "prop_gate_passed": true,
        "prop_gate_reason": "ok",
        "slot_weight": 1.585,
        "slot_weight_basis_points": 1585,
        "slot_weight_inputs": {
          "citation_weight": 1.0,
          "dependency_depth": 1,
          "direct_dependency_count": 0,
          "import_breadth": 1,
          "import_depth": 0,
          "import_graph_entries": 16,
          "import_graph_resolved": true,
          "import_graph_sha256": "8acf594d0f836405445898da44f610f628851b071c10767b3518c35e4025dcb7",
          "import_graph_version": "lemma-import-graph-v1",
          "kernel_dependencies_recorded": false,
          "lemma_rows_used_count": 0,
          "missing_import_count": 0,
          "mutation_depth": 2,
          "transitive_dependency_count": 0,
          "transitive_dependency_hash": "c6ed27a96ba867f17c27281e11405b28cf8dfd2a97c1ed75e5cead902eb8074a"
        },
        "slot_weight_version": "lemma-slot-weight-v3",
        "source_pool_hash": "180508097fb11c3c12f416833b077bfdd40da9fbbdb54c3e72572a4969d6efe0",
        "source_pool_receipt_sha256": "bc9f8af90992a8a5ef66e42d66c2c0acecd322124b53d2042636c4195edb2d63",
        "source_pool_receipt_version": "lemma-source-pool-receipt-v1",
        "source_pool_source_count": 39,
        "source_pool_stream_counts": {
          "mathlib_snapshot": 39
        },
        "source_sampling_version": "lemma-source-sampling-v1",
        "source_target_sha256": "46fda61b5bf684067dbb79be6cc3ccf82f05b6915d0599f1fde4d3c80a1264dc",
        "source_task_id": "lemma.mathlib_snapshot.noZeroDivisors_tfae",
        "source_theorem_name": "noZeroDivisors_tfae",
        "statement_hash": "04ddedc8ffcd40dcc09f19beccf56b4368e8d833df221f5ef8662c51b66455d4",
        "supply_mode": "procedural",
        "tempo": 20005,
        "triviality_budget_heartbeats": 200000,
        "triviality_budget_s": 200000,
        "triviality_budget_version": "lemma-triviality-retarget-v1",
        "triviality_burn_rate_basis_points": null,
        "triviality_checked": true,
        "triviality_reason": "baseline_failed",
        "triviality_retarget_inputs": {
          "genesis_budget_heartbeats": 200000,
          "genesis_budget_s": 200000,
          "high_burn_basis_points": 7000,
          "latest_settlement_tempo": null,
          "low_burn_basis_points": 4000,
          "max_budget_heartbeats": 2000000,
          "max_budget_s": 2000000,
          "max_step_basis_points": 2500,
          "min_budget_heartbeats": 20000,
          "min_budget_s": 20000,
          "settlement_count": 0,
          "settlement_history_sha256": "4f53cda18c2baa0c0354bb5f9a3ecbe5ed12ab4d8e11ba873c2f11161202b945",
          "target_burn_basis_points": 5500,
          "target_tempo": 20005,
          "version": "lemma-triviality-retarget-v1",
          "window_tempos": 8
        },
        "triviality_stack": [
          "decide",
          "simp_all",
          "omega",
          "norm_num",
          "ring",
          "linarith",
          "nlinarith",
          "aesop"
        ],
        "typecheck_reason": "ok",
        "typechecked": true
      },
      "policy": "restricted_helpers",
      "queue_depth": 1,
      "queue_position": 2,
      "schema_version": 1,
      "source_license": "Apache-2.0",
      "source_ref": {
        "commit": "5450b53e5ddc75d46418fabb605edbf36bd0beb6",
        "kind": "procedural",
        "name": "tempo-20005-seq-9",
        "path": "Mathlib/Algebra/Ring/Basic.lean"
      },
      "source_stream": "procedural",
      "statement": "theorem procedural_noZeroDivisors_tfae_1fafeb8df263 : (\u2200 lemma_p0_a6a8d5 : Prop,\n    lemma_p0_a6a8d5 \u2192\n      (\u2200 {R : Type _} [NonUnitalNonAssocRing R],\n        [NoZeroDivisors R, IsLeftCancelMulZero R, IsRightCancelMulZero R, IsCancelMulZero R].TFAE)) \u2228\n  False := by\n  sorry",
      "submission_stub": "import Mathlib.Algebra.Ring.Basic\n\nnamespace Submission\n\ntheorem procedural_noZeroDivisors_tfae_1fafeb8df263 : (\u2200 lemma_p0_a6a8d5 : Prop,\n    lemma_p0_a6a8d5 \u2192\n      (\u2200 {R : Type _} [NonUnitalNonAssocRing R],\n        [NoZeroDivisors R, IsLeftCancelMulZero R, IsRightCancelMulZero R, IsCancelMulZero R].TFAE)) \u2228\n  False := by\n  sorry\n\nend Submission\n",
      "target_sha256": "02c31e27256977aa24faa9f5e29147ec6249550c106cc6233bb542d710fcc3ef",
      "task_version": 1,
      "theorem_name": "procedural_noZeroDivisors_tfae_1fafeb8df263",
      "title": "Procedural noZeroDivisors_tfae",
      "triviality_status": "paid_easy",
      "type_expr": "(\u2200 lemma_p0_a6a8d5 : Prop,\n    lemma_p0_a6a8d5 \u2192\n      (\u2200 {R : Type _} [NonUnitalNonAssocRing R],\n        [NoZeroDivisors R, IsLeftCancelMulZero R, IsRightCancelMulZero R, IsCancelMulZero R].TFAE)) \u2228\n  False",
      "verifier_id": "lake-build",
      "verifier_version": "lemma-lean-v1"
    },
    {
      "activation_status": "paid",
      "difficulty_band": "easy",
      "domain_id": "lean",
      "frontier_depth": 14,
      "id": "lemma.procedural.df298446619dae40",
      "imports": [
        "Mathlib.Algebra.Ring.Basic",
        "Mathlib.Algebra.Ring.Associator",
        "Mathlib.Algebra.Ring.Aut"
      ],
      "lean_toolchain": "leanprover/lean4:v4.30.0-rc2",
      "mathlib_rev": "5450b53e5ddc75d46418fabb605edbf36bd0beb6",
      "metadata": {
        "activation_status": "paid",
        "anchor_block": 7201800,
        "baseline_solved": false,
        "baseline_solver": null,
        "canonical_hash": "756a1ddd4eaeb8e9ab71b451647f7710a9e97848f71cc6cbac4c67fc5d3374fd",
        "citation_alpha_basis_points": 5000,
        "citation_weight_cap_micros": 64000000,
        "citation_window_tempos": 2000,
        "drand_round": 28980552,
        "gate_receipt_sha256": "bdd7b78b94063acc262bbfa2a3064c9fa10d7eeb2080f0604abd4823f51a0cba",
        "gate_runner": "lean",
        "gate_version": "lemma-procedural-gates-v3",
        "generation_seed": "fe40d272cad1d59ab1869a8489d908fc5c32848a13501244397700f4ccd24831",
        "kernel_canonical_hash": "756a1ddd4eaeb8e9ab71b451647f7710a9e97848f71cc6cbac4c67fc5d3374fd",
        "kernel_canonical_name": "LemmaProceduralGate.kernel_normal_form",
        "license_state": "clean_open",
        "mutation_chain": [
          {
            "input_hash": "2ebf646eda400a6b1b0c29c505aadbab2afa5ab3d68b32cc99677b5c14905013",
            "operator": "strengthen",
            "output_hash": "d7df4c7875d73f405233c0bde8dbed18213243c9ed46778ff03075261f5c4986",
            "params": {
              "engine": "lean_ast_elaborator",
              "peer_source_id": "lemma.mathlib_snapshot.associator_apply",
              "peer_target_sha256": "afbd7f741deb88d8067249e20d8ea2d1d290ee304b4bb99d6440eb3f4e3e2fd5",
              "peer_theorem_name": "associator_apply",
              "rule": "conjoin_peer_conclusion"
            }
          },
          {
            "input_hash": "d7df4c7875d73f405233c0bde8dbed18213243c9ed46778ff03075261f5c4986",
            "operator": "strengthen",
            "output_hash": "58051858d1d0a2f2fc67a082c9c1e5604092bd88c2b184474168ff5b89d2c59d",
            "params": {
              "engine": "lean_ast_elaborator",
              "peer_source_id": "lemma.mathlib_snapshot.RingAut.coe_pow",
              "peer_target_sha256": "fa8c16f10bb06e1bf477bacf72a04c309045bb6855e63c7d32f69ea2f4310a1a",
              "peer_theorem_name": "RingAut.coe_pow",
              "rule": "conjoin_peer_conclusion"
            }
          }
        ],
        "mutation_depth": 2,
        "novelty_cache_entries": 1,
        "novelty_cache_sha256": "1e32c7405aa77f76d3d5a318d9d8882ceff2219062dbdf0d4471f64b49267ccd",
        "novelty_cache_version": "lemma-novelty-cache-v1",
        "novelty_status": "passed",
        "operator_bundle_hash": "f8d88c884199c0ffe47fc0089803a5d38c1bf8b38395162a298a5c65e04592e1",
        "operator_bundle_version": "lemma-procedural-depth2-v3",
        "prop_gate_passed": true,
        "prop_gate_reason": "ok",
        "slot_weight": 1.635,
        "slot_weight_basis_points": 1635,
        "slot_weight_inputs": {
          "citation_weight": 1.0,
          "dependency_depth": 1,
          "direct_dependency_count": 0,
          "import_breadth": 3,
          "import_depth": 0,
          "import_graph_entries": 16,
          "import_graph_resolved": true,
          "import_graph_sha256": "8acf594d0f836405445898da44f610f628851b071c10767b3518c35e4025dcb7",
          "import_graph_version": "lemma-import-graph-v1",
          "kernel_dependencies_recorded": false,
          "lemma_rows_used_count": 0,
          "missing_import_count": 0,
          "mutation_depth": 2,
          "transitive_dependency_count": 0,
          "transitive_dependency_hash": "1497caca6e83a736ccd1bb6dd0a23ddb2e7efd59d09e7ab9d6cdc4f23a929cbf"
        },
        "slot_weight_version": "lemma-slot-weight-v3",
        "source_pool_hash": "180508097fb11c3c12f416833b077bfdd40da9fbbdb54c3e72572a4969d6efe0",
        "source_pool_receipt_sha256": "bc9f8af90992a8a5ef66e42d66c2c0acecd322124b53d2042636c4195edb2d63",
        "source_pool_receipt_version": "lemma-source-pool-receipt-v1",
        "source_pool_source_count": 39,
        "source_pool_stream_counts": {
          "mathlib_snapshot": 39
        },
        "source_sampling_version": "lemma-source-sampling-v1",
        "source_target_sha256": "7728890a39f50ef96967c78d1360e69e9aa911a2803c47aecf8cb5159854e226",
        "source_task_id": "lemma.mathlib_snapshot.isDomain_iff_noZeroDivisors_and_nontrivial",
        "source_theorem_name": "isDomain_iff_noZeroDivisors_and_nontrivial",
        "statement_hash": "d945ac22d129ded8f484e891240062c71b7d897c1c170647309cda6cb3a18475",
        "supply_mode": "procedural",
        "tempo": 20005,
        "triviality_budget_heartbeats": 200000,
        "triviality_budget_s": 200000,
        "triviality_budget_version": "lemma-triviality-retarget-v1",
        "triviality_burn_rate_basis_points": null,
        "triviality_checked": true,
        "triviality_reason": "baseline_failed",
        "triviality_retarget_inputs": {
          "genesis_budget_heartbeats": 200000,
          "genesis_budget_s": 200000,
          "high_burn_basis_points": 7000,
          "latest_settlement_tempo": null,
          "low_burn_basis_points": 4000,
          "max_budget_heartbeats": 2000000,
          "max_budget_s": 2000000,
          "max_step_basis_points": 2500,
          "min_budget_heartbeats": 20000,
          "min_budget_s": 20000,
          "settlement_count": 0,
          "settlement_history_sha256": "4f53cda18c2baa0c0354bb5f9a3ecbe5ed12ab4d8e11ba873c2f11161202b945",
          "target_burn_basis_points": 5500,
          "target_tempo": 20005,
          "version": "lemma-triviality-retarget-v1",
          "window_tempos": 8
        },
        "triviality_stack": [
          "decide",
          "simp_all",
          "omega",
          "norm_num",
          "ring",
          "linarith",
          "nlinarith",
          "aesop"
        ],
        "typecheck_reason": "ok",
        "typechecked": true
      },
      "policy": "restricted_helpers",
      "queue_depth": 1,
      "queue_position": 3,
      "schema_version": 1,
      "source_license": "Apache-2.0",
      "source_ref": {
        "commit": "5450b53e5ddc75d46418fabb605edbf36bd0beb6",
        "kind": "procedural",
        "name": "tempo-20005-seq-7",
        "path": "Mathlib/Algebra/Ring/Basic.lean"
      },
      "source_stream": "procedural",
      "statement": "theorem procedural_isDomain_iff_noZeroDivisors_and_nontrivial_df298446619d : ((\u2200 (\u03b1 : Type _) [Ring \u03b1], IsDomain \u03b1 \u2194 NoZeroDivisors \u03b1 \u2227 Nontrivial \u03b1) \u2227\n    (\u2200 {R : Type _} [NonUnitalNonAssocRing R] (x y z : R), associator x y z = x * y * z - x * (y * z))) \u2227\n  (\u2200 {R : Type _} [Mul R] [Add R] (f : R \u2243+* R) (n : \u2115), \u21d1(f ^ n) = (\u21d1f)^[n]) := by\n  sorry",
      "submission_stub": "import Mathlib.Algebra.Ring.Basic\nimport Mathlib.Algebra.Ring.Associator\nimport Mathlib.Algebra.Ring.Aut\n\nnamespace Submission\n\ntheorem procedural_isDomain_iff_noZeroDivisors_and_nontrivial_df298446619d : ((\u2200 (\u03b1 : Type _) [Ring \u03b1], IsDomain \u03b1 \u2194 NoZeroDivisors \u03b1 \u2227 Nontrivial \u03b1) \u2227\n    (\u2200 {R : Type _} [NonUnitalNonAssocRing R] (x y z : R), associator x y z = x * y * z - x * (y * z))) \u2227\n  (\u2200 {R : Type _} [Mul R] [Add R] (f : R \u2243+* R) (n : \u2115), \u21d1(f ^ n) = (\u21d1f)^[n]) := by\n  sorry\n\nend Submission\n",
      "target_sha256": "1f65e709178bf9fa647ce9768ac84ad91fa96c9c4b8cf7727ebeab6623d4a83d",
      "task_version": 1,
      "theorem_name": "procedural_isDomain_iff_noZeroDivisors_and_nontrivial_df298446619d",
      "title": "Procedural isDomain_iff_noZeroDivisors_and_nontrivial",
      "triviality_status": "paid_easy",
      "type_expr": "((\u2200 (\u03b1 : Type _) [Ring \u03b1], IsDomain \u03b1 \u2194 NoZeroDivisors \u03b1 \u2227 Nontrivial \u03b1) \u2227\n    (\u2200 {R : Type _} [NonUnitalNonAssocRing R] (x y z : R), associator x y z = x * y * z - x * (y * z))) \u2227\n  (\u2200 {R : Type _} [Mul R] [Add R] (f : R \u2243+* R) (n : \u2115), \u21d1(f ^ n) = (\u21d1f)^[n])",
      "verifier_id": "lake-build",
      "verifier_version": "lemma-lean-v1"
    },
    {
      "activation_status": "paid",
      "difficulty_band": "medium",
      "domain_id": "lean",
      "frontier_depth": 14,
      "id": "lemma.procedural.64af5b296e3b8f1b",
      "imports": [
        "Mathlib.Algebra.Ring.Invertible",
        "Mathlib.Algebra.Ring.Centralizer",
        "Mathlib.Algebra.Ring.Associated"
      ],
      "lean_toolchain": "leanprover/lean4:v4.30.0-rc2",
      "mathlib_rev": "5450b53e5ddc75d46418fabb605edbf36bd0beb6",
      "metadata": {
        "activation_status": "paid",
        "anchor_block": 7201800,
        "baseline_solved": false,
        "baseline_solver": null,
        "canonical_hash": "df245e78e9e2bfa10deb88ec5acb9452ac6b6b7d6f68527003932627380ea6d1",
        "citation_alpha_basis_points": 5000,
        "citation_weight_cap_micros": 64000000,
        "citation_window_tempos": 2000,
        "drand_round": 28980552,
        "gate_receipt_sha256": "753116ce3702d5ebb71d955ae9be93021d1e736c4ff472bd471c44ff21be5d4c",
        "gate_runner": "lean",
        "gate_version": "lemma-procedural-gates-v3",
        "generation_seed": "fe40d272cad1d59ab1869a8489d908fc5c32848a13501244397700f4ccd24831",
        "kernel_canonical_hash": "df245e78e9e2bfa10deb88ec5acb9452ac6b6b7d6f68527003932627380ea6d1",
        "kernel_canonical_name": "LemmaProceduralGate.kernel_normal_form",
        "license_state": "clean_open",
        "mutation_chain": [
          {
            "input_hash": "39c082f7e2cb71c8486edc8af846f61cd8718a3b482db18ffcf42a68829bafc1",
            "operator": "generalize",
            "output_hash": "f052ac35abb392cfd586b38400645179b881d830fb05f9d2d56c2357a2612af3",
            "params": {
              "binder": "lemma_p0_p79861e",
              "binder_type": "Prop",
              "engine": "lean_ast_elaborator",
              "target": "fresh_prop_hypothesis"
            }
          },
          {
            "input_hash": "f052ac35abb392cfd586b38400645179b881d830fb05f9d2d56c2357a2612af3",
            "operator": "conjoin",
            "output_hash": "343c40415c3eb2dc758b10d5359af6ecedde9ddda2b4278907ea9960c508def2",
            "params": {
              "engine": "lean_ast_elaborator",
              "mode": "peer_premise",
              "peer_source_id": "lemma.mathlib_snapshot.Associated.neg_left_iff",
              "peer_target_sha256": "1e6f3ddf12b1e60edee4397c5aba57195e74d343f4cefc5cdcefe1567fa7eae5",
              "peer_theorem_name": "Associated.neg_left_iff"
            }
          }
        ],
        "mutation_depth": 2,
        "novelty_cache_entries": 1,
        "novelty_cache_sha256": "1e32c7405aa77f76d3d5a318d9d8882ceff2219062dbdf0d4471f64b49267ccd",
        "novelty_cache_version": "lemma-novelty-cache-v1",
        "novelty_status": "passed",
        "operator_bundle_hash": "f8d88c884199c0ffe47fc0089803a5d38c1bf8b38395162a298a5c65e04592e1",
        "operator_bundle_version": "lemma-procedural-depth2-v3",
        "prop_gate_passed": true,
        "prop_gate_reason": "ok",
        "slot_weight": 1.785,
        "slot_weight_basis_points": 1785,
        "slot_weight_inputs": {
          "citation_weight": 1.0,
          "dependency_depth": 2,
          "direct_dependency_count": 0,
          "import_breadth": 3,
          "import_depth": 0,
          "import_graph_entries": 16,
          "import_graph_resolved": true,
          "import_graph_sha256": "8acf594d0f836405445898da44f610f628851b071c10767b3518c35e4025dcb7",
          "import_graph_version": "lemma-import-graph-v1",
          "kernel_dependencies_recorded": false,
          "lemma_rows_used_count": 0,
          "missing_import_count": 0,
          "mutation_depth": 2,
          "transitive_dependency_count": 0,
          "transitive_dependency_hash": "c606c20dc18facd135a56f0922f5db48ec199561720454c1736e3b3923b083bf"
        },
        "slot_weight_version": "lemma-slot-weight-v3",
        "source_pool_hash": "180508097fb11c3c12f416833b077bfdd40da9fbbdb54c3e72572a4969d6efe0",
        "source_pool_receipt_sha256": "bc9f8af90992a8a5ef66e42d66c2c0acecd322124b53d2042636c4195edb2d63",
        "source_pool_receipt_version": "lemma-source-pool-receipt-v1",
        "source_pool_source_count": 39,
        "source_pool_stream_counts": {
          "mathlib_snapshot": 39
        },
        "source_sampling_version": "lemma-source-sampling-v1",
        "source_target_sha256": "7b7d61a4273a37e66ecb5f35bcb4835d6c00ab554af07f28946728ecb0cfa389",
        "source_task_id": "lemma.mathlib_snapshot.eq_of_invOf_add_eq_invOf_add_invOf",
        "source_theorem_name": "eq_of_invOf_add_eq_invOf_add_invOf",
        "statement_hash": "2e326125e4e54683625e8b4e32ddbce5607c75ffb4f5253ceeef1f1476ff9a5d",
        "supply_mode": "procedural",
        "tempo": 20005,
        "triviality_budget_heartbeats": 200000,
        "triviality_budget_s": 200000,
        "triviality_budget_version": "lemma-triviality-retarget-v1",
        "triviality_burn_rate_basis_points": null,
        "triviality_checked": true,
        "triviality_reason": "baseline_failed",
        "triviality_retarget_inputs": {
          "genesis_budget_heartbeats": 200000,
          "genesis_budget_s": 200000,
          "high_burn_basis_points": 7000,
          "latest_settlement_tempo": null,
          "low_burn_basis_points": 4000,
          "max_budget_heartbeats": 2000000,
          "max_budget_s": 2000000,
          "max_step_basis_points": 2500,
          "min_budget_heartbeats": 20000,
          "min_budget_s": 20000,
          "settlement_count": 0,
          "settlement_history_sha256": "4f53cda18c2baa0c0354bb5f9a3ecbe5ed12ab4d8e11ba873c2f11161202b945",
          "target_burn_basis_points": 5500,
          "target_tempo": 20005,
          "version": "lemma-triviality-retarget-v1",
          "window_tempos": 8
        },
        "triviality_stack": [
          "decide",
          "simp_all",
          "omega",
          "norm_num",
          "ring",
          "linarith",
          "nlinarith",
          "aesop"
        ],
        "typecheck_reason": "ok",
        "typechecked": true
      },
      "policy": "restricted_helpers",
      "queue_depth": 2,
      "queue_position": 4,
      "schema_version": 1,
      "source_license": "Apache-2.0",
      "source_ref": {
        "commit": "5450b53e5ddc75d46418fabb605edbf36bd0beb6",
        "kind": "procedural",
        "name": "tempo-20005-seq-0",
        "path": "Mathlib/Algebra/Ring/Invertible.lean"
      },
      "source_stream": "procedural",
      "statement": "theorem procedural_eq_of_invOf_add_eq_invOf_add_invOf_64af5b296e3b : (\u2200 {M : Type _} [Monoid M] [HasDistribNeg M] {a b : M}, Associated (-a) b \u2194 Associated a b) \u2192\n  (\u2200 lemma_p0_p79861e : Prop,\n    lemma_p0_p79861e \u2192\n      (\u2200 {R : Type _} [Ring R] {a b : R} [Invertible a] [Invertible b] [Invertible (a + b)] (h : \u215f(a + b) = \u215fa + \u215fb),\n        a * \u215fb * a = b * \u215fa * b)) := by\n  sorry",
      "submission_stub": "import Mathlib.Algebra.Ring.Invertible\nimport Mathlib.Algebra.Ring.Centralizer\nimport Mathlib.Algebra.Ring.Associated\n\nnamespace Submission\n\ntheorem procedural_eq_of_invOf_add_eq_invOf_add_invOf_64af5b296e3b : (\u2200 {M : Type _} [Monoid M] [HasDistribNeg M] {a b : M}, Associated (-a) b \u2194 Associated a b) \u2192\n  (\u2200 lemma_p0_p79861e : Prop,\n    lemma_p0_p79861e \u2192\n      (\u2200 {R : Type _} [Ring R] {a b : R} [Invertible a] [Invertible b] [Invertible (a + b)] (h : \u215f(a + b) = \u215fa + \u215fb),\n        a * \u215fb * a = b * \u215fa * b)) := by\n  sorry\n\nend Submission\n",
      "target_sha256": "5d4bbaf6c4000e07dc68920229c771d7345bf098e807dddf7464739df973b856",
      "task_version": 1,
      "theorem_name": "procedural_eq_of_invOf_add_eq_invOf_add_invOf_64af5b296e3b",
      "title": "Procedural eq_of_invOf_add_eq_invOf_add_invOf",
      "triviality_status": "paid_medium",
      "type_expr": "(\u2200 {M : Type _} [Monoid M] [HasDistribNeg M] {a b : M}, Associated (-a) b \u2194 Associated a b) \u2192\n  (\u2200 lemma_p0_p79861e : Prop,\n    lemma_p0_p79861e \u2192\n      (\u2200 {R : Type _} [Ring R] {a b : R} [Invertible a] [Invertible b] [Invertible (a + b)] (h : \u215f(a + b) = \u215fa + \u215fb),\n        a * \u215fb * a = b * \u215fa * b))",
      "verifier_id": "lake-build",
      "verifier_version": "lemma-lean-v1"
    },
    {
      "activation_status": "paid",
      "difficulty_band": "medium",
      "domain_id": "lean",
      "frontier_depth": 14,
      "id": "lemma.procedural.5f09d4a98ae525d3",
      "imports": [
        "Mathlib.Algebra.Ring.Idempotent",
        "Mathlib.Algebra.Ring.SumsOfSquares",
        "Mathlib.Algebra.Ring.Basic"
      ],
      "lean_toolchain": "leanprover/lean4:v4.30.0-rc2",
      "mathlib_rev": "5450b53e5ddc75d46418fabb605edbf36bd0beb6",
      "metadata": {
        "activation_status": "paid",
        "anchor_block": 7201800,
        "baseline_solved": false,
        "baseline_solver": null,
        "canonical_hash": "0b08e7326c867ddd7f2eed167c8674be83edcc3053f83e71a0be75b5d4bf86cf",
        "citation_alpha_basis_points": 5000,
        "citation_weight_cap_micros": 64000000,
        "citation_window_tempos": 2000,
        "drand_round": 28980552,
        "gate_receipt_sha256": "2e42b86bbeb6d8ebf4f66b18d5f3f6c968384c21848b02d0a1b23eefdf44f0e7",
        "gate_runner": "lean",
        "gate_version": "lemma-procedural-gates-v3",
        "generation_seed": "fe40d272cad1d59ab1869a8489d908fc5c32848a13501244397700f4ccd24831",
        "kernel_canonical_hash": "0b08e7326c867ddd7f2eed167c8674be83edcc3053f83e71a0be75b5d4bf86cf",
        "kernel_canonical_name": "LemmaProceduralGate.kernel_normal_form",
        "license_state": "clean_open",
        "mutation_chain": [
          {
            "input_hash": "3bd36a9388c61a41cb1f696fba722d5cf61291966c5ce80efde7d177599d8e58",
            "operator": "generalize",
            "output_hash": "a735c86bf4ce8a55b21ce9e8e1c0b177c26f8214d0769d5cb3588a5b993d9fe2",
            "params": {
              "binder": "lemma_p0_a69432",
              "binder_type": "Prop",
              "engine": "lean_ast_elaborator",
              "target": "fresh_prop_hypothesis"
            }
          },
          {
            "input_hash": "a735c86bf4ce8a55b21ce9e8e1c0b177c26f8214d0769d5cb3588a5b993d9fe2",
            "operator": "generalize",
            "output_hash": "1b12bb7fddd476bc1be61d725e780542ff525a3d3a6dc2518fb3088593f72ff9",
            "params": {
              "binder": "lemma_p1_p54b161",
              "binder_type": "Prop",
              "engine": "lean_ast_elaborator",
              "target": "fresh_prop_hypothesis"
            }
          }
        ],
        "mutation_depth": 2,
        "novelty_cache_entries": 1,
        "novelty_cache_sha256": "1e32c7405aa77f76d3d5a318d9d8882ceff2219062dbdf0d4471f64b49267ccd",
        "novelty_cache_version": "lemma-novelty-cache-v1",
        "novelty_status": "passed",
        "operator_bundle_hash": "f8d88c884199c0ffe47fc0089803a5d38c1bf8b38395162a298a5c65e04592e1",
        "operator_bundle_version": "lemma-procedural-depth2-v3",
        "prop_gate_passed": true,
        "prop_gate_reason": "ok",
        "slot_weight": 1.785,
        "slot_weight_basis_points": 1785,
        "slot_weight_inputs": {
          "citation_weight": 1.0,
          "dependency_depth": 2,
          "direct_dependency_count": 0,
          "import_breadth": 3,
          "import_depth": 0,
          "import_graph_entries": 16,
          "import_graph_resolved": true,
          "import_graph_sha256": "8acf594d0f836405445898da44f610f628851b071c10767b3518c35e4025dcb7",
          "import_graph_version": "lemma-import-graph-v1",
          "kernel_dependencies_recorded": false,
          "lemma_rows_used_count": 0,
          "missing_import_count": 0,
          "mutation_depth": 2,
          "transitive_dependency_count": 0,
          "transitive_dependency_hash": "bb904da3ba45e2547eb5e8452b5a3b5afcc98660098c0bd498b386af297bc7ba"
        },
        "slot_weight_version": "lemma-slot-weight-v3",
        "source_pool_hash": "180508097fb11c3c12f416833b077bfdd40da9fbbdb54c3e72572a4969d6efe0",
        "source_pool_receipt_sha256": "bc9f8af90992a8a5ef66e42d66c2c0acecd322124b53d2042636c4195edb2d63",
        "source_pool_receipt_version": "lemma-source-pool-receipt-v1",
        "source_pool_source_count": 39,
        "source_pool_stream_counts": {
          "mathlib_snapshot": 39
        },
        "source_sampling_version": "lemma-source-sampling-v1",
        "source_target_sha256": "1f8babd00b3922c0e707a4514ac1ad31ca2924eb3b4f4957a7c50c7af0e02ec2",
        "source_task_id": "lemma.mathlib_snapshot.IsIdempotentElem.sub_iff",
        "source_theorem_name": "IsIdempotentElem.sub_iff",
        "statement_hash": "58056493e645ef944692270dc8318dc3529c809ce6f3e6e3f493c2244d8a943e",
        "supply_mode": "procedural",
        "tempo": 20005,
        "triviality_budget_heartbeats": 200000,
        "triviality_budget_s": 200000,
        "triviality_budget_version": "lemma-triviality-retarget-v1",
        "triviality_burn_rate_basis_points": null,
        "triviality_checked": true,
        "triviality_reason": "baseline_failed",
        "triviality_retarget_inputs": {
          "genesis_budget_heartbeats": 200000,
          "genesis_budget_s": 200000,
          "high_burn_basis_points": 7000,
          "latest_settlement_tempo": null,
          "low_burn_basis_points": 4000,
          "max_budget_heartbeats": 2000000,
          "max_budget_s": 2000000,
          "max_step_basis_points": 2500,
          "min_budget_heartbeats": 20000,
          "min_budget_s": 20000,
          "settlement_count": 0,
          "settlement_history_sha256": "4f53cda18c2baa0c0354bb5f9a3ecbe5ed12ab4d8e11ba873c2f11161202b945",
          "target_burn_basis_points": 5500,
          "target_tempo": 20005,
          "version": "lemma-triviality-retarget-v1",
          "window_tempos": 8
        },
        "triviality_stack": [
          "decide",
          "simp_all",
          "omega",
          "norm_num",
          "ring",
          "linarith",
          "nlinarith",
          "aesop"
        ],
        "typecheck_reason": "ok",
        "typechecked": true
      },
      "policy": "restricted_helpers",
      "queue_depth": 2,
      "queue_position": 5,
      "schema_version": 1,
      "source_license": "Apache-2.0",
      "source_ref": {
        "commit": "5450b53e5ddc75d46418fabb605edbf36bd0beb6",
        "kind": "procedural",
        "name": "tempo-20005-seq-4",
        "path": "Mathlib/Algebra/Ring/Idempotent.lean"
      },
      "source_stream": "procedural",
      "statement": "theorem procedural_IsIdempotentElem_sub_iff_5f09d4a98ae5 : \u2200 lemma_p1_p54b161 : Prop,\n  lemma_p1_p54b161 \u2192\n    (\u2200 lemma_p0_a69432 : Prop,\n      lemma_p0_a69432 \u2192\n        (\u2200 {R : Type _} [NonUnitalRing R] [IsAddTorsionFree R] {p q : R} (hp : IsIdempotentElem p)\n          (hq : IsIdempotentElem q), IsIdempotentElem (q - p) \u2194 p * q = p \u2227 q * p = p)) := by\n  sorry",
      "submission_stub": "import Mathlib.Algebra.Ring.Idempotent\nimport Mathlib.Algebra.Ring.SumsOfSquares\nimport Mathlib.Algebra.Ring.Basic\n\nnamespace Submission\n\ntheorem procedural_IsIdempotentElem_sub_iff_5f09d4a98ae5 : \u2200 lemma_p1_p54b161 : Prop,\n  lemma_p1_p54b161 \u2192\n    (\u2200 lemma_p0_a69432 : Prop,\n      lemma_p0_a69432 \u2192\n        (\u2200 {R : Type _} [NonUnitalRing R] [IsAddTorsionFree R] {p q : R} (hp : IsIdempotentElem p)\n          (hq : IsIdempotentElem q), IsIdempotentElem (q - p) \u2194 p * q = p \u2227 q * p = p)) := by\n  sorry\n\nend Submission\n",
      "target_sha256": "1bbe242985b46c925e90de9937aba39f0dbf23c5d68565d605333761e73ef8b4",
      "task_version": 1,
      "theorem_name": "procedural_IsIdempotentElem_sub_iff_5f09d4a98ae5",
      "title": "Procedural IsIdempotentElem.sub_iff",
      "triviality_status": "paid_medium",
      "type_expr": "\u2200 lemma_p1_p54b161 : Prop,\n  lemma_p1_p54b161 \u2192\n    (\u2200 lemma_p0_a69432 : Prop,\n      lemma_p0_a69432 \u2192\n        (\u2200 {R : Type _} [NonUnitalRing R] [IsAddTorsionFree R] {p q : R} (hp : IsIdempotentElem p)\n          (hq : IsIdempotentElem q), IsIdempotentElem (q - p) \u2194 p * q = p \u2227 q * p = p))",
      "verifier_id": "lake-build",
      "verifier_version": "lemma-lean-v1"
    }
  ]
}
